cli/__init__.py
cli/layeredpy.py
constants/__init__.py
constants/templates.py
layered_py/__init__.py
layered_py/bootstrap.py
layered_py/config_loader.py
layered_py/decorators.py
layered_py/di.py
layered_py/domain.py
layered_py/generator.py
layered_py/presentation.py
layered_py/repository.py
layered_py/service.py
layered_py/shared.py
layered_py-3.0.1.dist-info/licenses/LICENSE
layered_py-3.0.1.dist-info/METADATA
layered_py-3.0.1.dist-info/WHEEL
layered_py-3.0.1.dist-info/entry_points.txt
layered_py-3.0.1.dist-info/top_level.txt
layered_py-3.0.1.dist-info/RECORD
