Metadata-Version: 2.4
Name: layered-py
Version: 3.0.1
Summary: A Python library for implementing layered architecture with services and dependency injection.
Home-page: https://github.com/upNorthDev/LayeredPy
Author: Malte Harms
Author-email: mail@malteharms.dev
Project-URL: Bug Tracker, https://github.com/upNorthDev/LayeredPy/issues
Project-URL: Documentation, https://github.com/upNorthDev/LayeredPy
Project-URL: Source Code, https://github.com/upNorthDev/LayeredPy
Keywords: layered architecture,services,dependency injection,python
Classifier: Programming Language :: Python
Classifier: Programming Language :: Python :: 3
Classifier: Programming Language :: Python :: 3.7
Classifier: Programming Language :: Python :: 3.8
Classifier: Programming Language :: Python :: 3.9
Classifier: Programming Language :: Python :: 3.10
Classifier: Programming Language :: Python :: 3.11
Classifier: Development Status :: 5 - Production/Stable
Classifier: Intended Audience :: Developers
Classifier: License :: OSI Approved :: MIT License
Classifier: Operating System :: OS Independent
Requires-Python: >=3.7
License-File: LICENSE
Dynamic: author
Dynamic: author-email
Dynamic: classifier
Dynamic: description
Dynamic: description-content-type
Dynamic: home-page
Dynamic: keywords
Dynamic: license-file
Dynamic: project-url
Dynamic: requires-python
Dynamic: summary
